tdameritrade_ext/__init__.py
tdameritrade_ext/_version.py
tdameritrade_ext/client.py
tdameritrade_ext/enums.py
tdameritrade_ext/exceptions.py
tdameritrade_ext/order.py
tdameritrade_ext/session.py
tdameritrade_ext/streaming.py
tdameritrade_ext/urls.py
tdameritrade_ext/auth/__init__.py
tdameritrade_ext/auth/__main__.py
tdameritrade_ext/orders/__init__.py
tdameritrade_ext/orders/constants.py
tdameritrade_ext/orders/leg_builder.py
tdameritrade_ext/orders/order_builder.py
tdameritrade_ext/orders/models/__init__.py
tdameritrade_ext/orders/models/activities.py
tdameritrade_ext/orders/models/base.py
tdameritrade_ext/orders/models/instruments.py
tdameritrade_ext/orders/models/json_encoder.py
tdameritrade_ext/orders/models/leg.py
tdameritrade_ext/orders/models/orders.py
tdameritrade_ext-0.0.2.dist-info/LICENSE
tdameritrade_ext-0.0.2.dist-info/METADATA
tdameritrade_ext-0.0.2.dist-info/WHEEL
tdameritrade_ext-0.0.2.dist-info/top_level.txt
tdameritrade_ext-0.0.2.dist-info/RECORD
