Metadata-Version: 2.1
Name: tdameritrade-ext
Version: 0.0.2
Summary: This package extend from https://github.com/timkpaine/tdameritrade.
Home-page: https://github.com/dearvn/tdameritrade_ext
Author: Donald
Author-email: donald.nguyen.it@gmail.com
License: MIT
Project-URL: Bug Tracker, https://github.com/dearvn/tdameritrade_ext/issues
Keywords: finance data,options data,crawl stock,tdameritrade
Platform: UNKNOWN
Classifier: License :: OSI Approved :: MIT License
Classifier: Development Status :: 3 - Alpha
Classifier: Programming Language :: Python :: 3
Classifier: Programming Language :: Python :: 3.6
Classifier: Programming Language :: Python :: 3.7
Classifier: Programming Language :: Python :: 3.8
Requires-Python: >=3.7.0
License-File: LICENSE
Requires-Dist: ipython (>=7.0.1)
Requires-Dist: pandas (>=0.22.0)
Requires-Dist: pillow (>=5.3.0)
Requires-Dist: requests (>=2.23.0)
Requires-Dist: selenium (>=3.141.0)
Requires-Dist: ujson (>=1.35)
Requires-Dist: black (>=20.)
Requires-Dist: bump2version (>=1.0.0)
Requires-Dist: flake8 (>=3.7.8)
Requires-Dist: flake8-black (>=0.2.1)
Requires-Dist: mock
Requires-Dist: pytest (>=4.3.0)
Requires-Dist: pytest-cov (>=2.6.1)
Requires-Dist: Sphinx (>=1.8.4)
Requires-Dist: sphinx-markdown-builder (>=0.5.2)
